rizval/__init__.py
rizval/rizval.py
rizval/types.py
rizval-0.0.1a0.dist-info/LICENSE
rizval-0.0.1a0.dist-info/METADATA
rizval-0.0.1a0.dist-info/WHEEL
rizval-0.0.1a0.dist-info/top_level.txt
rizval-0.0.1a0.dist-info/RECORD
