Metadata-Version: 2.1
Name: rizval
Version: 0.0.1a0
Summary: A data validation library inspired by JOI.
Home-page: https://github.com/rizwanmustafa/rizval
Author: Rizwan Mustafa
Author-email: rizwanmustafa0000@gmail.com
License: UNKNOWN
Project-URL: Bug Tracker, https://github.com/rizwanmustafa/rizval/issues
Platform: UNKNOWN
Classifier: Programming Language :: Python :: 3
Classifier: License :: OSI Approved :: MIT License
Classifier: Operating System :: OS Independent
Requires-Python: >=3.6
License-File: LICENSE
